{
  "lastUpdated": "2025-10-09T16:33:37.389Z",
  "volcanoes": [
    {
      "name": "Popocatépetl",
      "latitude": 19.0236,
      "longitude": -98.6225,
      "hourly": {
        "time": [
          "2025-10-09T00:00",
          "2025-10-09T01:00",
          "2025-10-09T02:00",
          "2025-10-09T03:00",
          "2025-10-09T04:00",
          "2025-10-09T05:00",
          "2025-10-09T06:00",
          "2025-10-09T07:00",
          "2025-10-09T08:00",
          "2025-10-09T09:00",
          "2025-10-09T10:00",
          "2025-10-09T11:00",
          "2025-10-09T12:00",
          "2025-10-09T13:00",
          "2025-10-09T14:00",
          "2025-10-09T15:00",
          "2025-10-09T16:00",
          "2025-10-09T17:00",
          "2025-10-09T18:00",
          "2025-10-09T19:00",
          "2025-10-09T20:00",
          "2025-10-09T21:00",
          "2025-10-09T22:00",
          "2025-10-09T23:00"
        ],
        "sulphur_dioxide": [
          7,
          7.2,
          7.6,
          7.7,
          7.5,
          7.2,
          6.9,
          6.6,
          6.3,
          6.1,
          6,
          5.9,
          6,
          6.4,
          6.9,
          7,
          6.4,
          5.5,
          4.7,
          4.3,
          4.1,
          4.1,
          4.2,
          4.4
        ],
        "carbon_monoxide": [
          136,
          139,
          141,
          143,
          143,
          142,
          143,
          147,
          153,
          160,
          170,
          180,
          183,
          173,
          157,
          143,
          134,
          127,
          126,
          137,
          154,
          166,
          168,
          165
        ],
        "nitrogen_dioxide": [
          30.7,
          29.7,
          28.3,
          26.9,
          25.6,
          24.3,
          23,
          21.4,
          19.8,
          18.6,
          18.2,
          18.3,
          18.4,
          18.8,
          19.3,
          18.8,
          16.2,
          12.6,
          9.8,
          8.1,
          7.2,
          8.2,
          12,
          17.7
        ],
        "carbon_dioxide": [
          438,
          442,
          447,
          450,
          451,
          450,
          450,
          450,
          451,
          452,
          455,
          459,
          459,
          452,
          442,
          434,
          432,
          434,
          435,
          435,
          434,
          434,
          434,
          435
        ],
        "wind_speed_10m": [
          5.9,
          6.3,
          7.6,
          7.9,
          7.3,
          8.4,
          8,
          9.4,
          7.9,
          8.2,
          4.1,
          5.4,
          8.7,
          7.6,
          5.6,
          6.2,
          4.5,
          4.6,
          5.3,
          6.4,
          5.4,
          3.3,
          3.1,
          3.7
        ],
        "wind_direction_10m": [
          11,
          31,
          19,
          24,
          20,
          25,
          36,
          40,
          39,
          52,
          38,
          70,
          73,
          71,
          63,
          54,
          76,
          135,
          152,
          164,
          176,
          139,
          135,
          151
        ]
      },
      "hourly_units": {
        "time": "iso8601",
        "sulphur_dioxide": "μg/m³",
        "carbon_monoxide": "μg/m³",
        "nitrogen_dioxide": "μg/m³",
        "carbon_dioxide": "ppm",
        "wind_speed_10m": "km/h",
        "wind_direction_10m": "°"
      }
    },
    {
      "name": "Fuego",
      "latitude": 14.473,
      "longitude": -90.88,
      "hourly": {
        "time": [
          "2025-10-09T00:00",
          "2025-10-09T01:00",
          "2025-10-09T02:00",
          "2025-10-09T03:00",
          "2025-10-09T04:00",
          "2025-10-09T05:00",
          "2025-10-09T06:00",
          "2025-10-09T07:00",
          "2025-10-09T08:00",
          "2025-10-09T09:00",
          "2025-10-09T10:00",
          "2025-10-09T11:00",
          "2025-10-09T12:00",
          "2025-10-09T13:00",
          "2025-10-09T14:00",
          "2025-10-09T15:00",
          "2025-10-09T16:00",
          "2025-10-09T17:00",
          "2025-10-09T18:00",
          "2025-10-09T19:00",
          "2025-10-09T20:00",
          "2025-10-09T21:00",
          "2025-10-09T22:00",
          "2025-10-09T23:00"
        ],
        "sulphur_dioxide": [
          9.4,
          10.2,
          11.3,
          12,
          12.2,
          11.9,
          11.2,
          9.5,
          7.2,
          5.7,
          4.9,
          4.8,
          6.5,
          11.3,
          17.9,
          23.5,
          27.4,
          30.3,
          30.9,
          28,
          23,
          18.4,
          15.3,
          12.7
        ],
        "carbon_monoxide": [
          314,
          423,
          558,
          669,
          749,
          806,
          815,
          745,
          628,
          533,
          497,
          483,
          451,
          373,
          276,
          202,
          171,
          164,
          162,
          149,
          142,
          175,
          286,
          437
        ],
        "nitrogen_dioxide": [
          15.4,
          25.5,
          39.1,
          47.7,
          46.4,
          40,
          34.2,
          31.1,
          28.6,
          26.6,
          25.8,
          25.4,
          23.6,
          18.5,
          11.9,
          7,
          5.2,
          5,
          5.1,
          4.7,
          4.5,
          5.5,
          8.1,
          11.9
        ],
        "carbon_dioxide": [
          438,
          446,
          456,
          465,
          473,
          481,
          486,
          487,
          487,
          486,
          489,
          492,
          488,
          469,
          443,
          424,
          420,
          424,
          426,
          424,
          420,
          419,
          422,
          427
        ],
        "wind_speed_10m": [
          6.4,
          3.4,
          1.5,
          2.9,
          4,
          4.1,
          4.7,
          4.9,
          5.5,
          6.2,
          6.8,
          7.1,
          7.1,
          5.9,
          2.3,
          2.3,
          2.1,
          4.7,
          6.9,
          8.9,
          9.1,
          8.2,
          5.1,
          1.5
        ],
        "wind_direction_10m": [
          232,
          238,
          284,
          353,
          5,
          15,
          9,
          17,
          23,
          21,
          18,
          15,
          15,
          11,
          321,
          219,
          211,
          212,
          208,
          212,
          214,
          221,
          219,
          225
        ]
      },
      "hourly_units": {
        "time": "iso8601",
        "sulphur_dioxide": "μg/m³",
        "carbon_monoxide": "μg/m³",
        "nitrogen_dioxide": "μg/m³",
        "carbon_dioxide": "ppm",
        "wind_speed_10m": "km/h",
        "wind_direction_10m": "°"
      }
    },
    {
      "name": "Reventador",
      "latitude": -0.0775,
      "longitude": -77.6561,
      "hourly": {
        "time": [
          "2025-10-09T00:00",
          "2025-10-09T01:00",
          "2025-10-09T02:00",
          "2025-10-09T03:00",
          "2025-10-09T04:00",
          "2025-10-09T05:00",
          "2025-10-09T06:00",
          "2025-10-09T07:00",
          "2025-10-09T08:00",
          "2025-10-09T09:00",
          "2025-10-09T10:00",
          "2025-10-09T11:00",
          "2025-10-09T12:00",
          "2025-10-09T13:00",
          "2025-10-09T14:00",
          "2025-10-09T15:00",
          "2025-10-09T16:00",
          "2025-10-09T17:00",
          "2025-10-09T18:00",
          "2025-10-09T19:00",
          "2025-10-09T20:00",
          "2025-10-09T21:00",
          "2025-10-09T22:00",
          "2025-10-09T23:00"
        ],
        "sulphur_dioxide": [
          2,
          2,
          2,
          2,
          1.9,
          1.8,
          1.7,
          1.6,
          1.6,
          1.6,
          1.3,
          1.1,
          1.7,
          4.1,
          7.4,
          9.6,
          9.7,
          8.7,
          7.5,
          6.1,
          4.5,
          3.2,
          2.6,
          2.3
        ],
        "carbon_monoxide": [
          986,
          855,
          703,
          594,
          559,
          566,
          586,
          620,
          666,
          689,
          674,
          635,
          578,
          475,
          352,
          298,
          340,
          450,
          628,
          929,
          1298,
          1575,
          1679,
          1691
        ],
        "nitrogen_dioxide": [
          5.6,
          6.4,
          7.5,
          8,
          7.5,
          6.5,
          5.5,
          4.7,
          3.9,
          3.4,
          3.4,
          3.7,
          3.6,
          2.8,
          1.7,
          0.8,
          0.5,
          0.4,
          0.5,
          0.5,
          0.6,
          1,
          2.1,
          3.6
        ],
        "carbon_dioxide": [
          432,
          441,
          453,
          462,
          468,
          472,
          475,
          476,
          476,
          473,
          467,
          458,
          449,
          438,
          427,
          419,
          417,
          419,
          420,
          419,
          418,
          418,
          421,
          425
        ],
        "wind_speed_10m": [
          2.2,
          3.3,
          4.2,
          4.8,
          4.4,
          4.5,
          5.2,
          3.7,
          3.6,
          3.3,
          3.2,
          1.5,
          1.1,
          3.3,
          4.5,
          6.5,
          6.7,
          7,
          6.6,
          6.2,
          6.5,
          5.9,
          5.4,
          4.5
        ],
        "wind_direction_10m": [
          360,
          311,
          290,
          283,
          279,
          284,
          282,
          281,
          276,
          264,
          270,
          256,
          108,
          84,
          104,
          90,
          74,
          78,
          77,
          80,
          90,
          79,
          86,
          61
        ]
      },
      "hourly_units": {
        "time": "iso8601",
        "sulphur_dioxide": "μg/m³",
        "carbon_monoxide": "μg/m³",
        "nitrogen_dioxide": "μg/m³",
        "carbon_dioxide": "ppm",
        "wind_speed_10m": "km/h",
        "wind_direction_10m": "°"
      }
    },
    {
      "name": "Kilauea",
      "latitude": 19.4069,
      "longitude": -155.2834,
      "hourly": {
        "time": [
          "2025-10-09T00:00",
          "2025-10-09T01:00",
          "2025-10-09T02:00",
          "2025-10-09T03:00",
          "2025-10-09T04:00",
          "2025-10-09T05:00",
          "2025-10-09T06:00",
          "2025-10-09T07:00",
          "2025-10-09T08:00",
          "2025-10-09T09:00",
          "2025-10-09T10:00",
          "2025-10-09T11:00",
          "2025-10-09T12:00",
          "2025-10-09T13:00",
          "2025-10-09T14:00",
          "2025-10-09T15:00",
          "2025-10-09T16:00",
          "2025-10-09T17:00",
          "2025-10-09T18:00",
          "2025-10-09T19:00",
          "2025-10-09T20:00",
          "2025-10-09T21:00",
          "2025-10-09T22:00",
          "2025-10-09T23:00"
        ],
        "sulphur_dioxide": [
          0.2,
          0.2,
          0.2,
          0.2,
          0.2,
          0.3,
          0.3,
          0.3,
          0.3,
          0.3,
          0.3,
          0.2,
          0.2,
          0.2,
          0.1,
          0.1,
          0.1,
          0.1,
          0.1,
          0.1,
          0.2,
          0.2,
          0.2,
          0.3
        ],
        "carbon_monoxide": [
          91,
          91,
          91,
          91,
          91,
          92,
          92,
          91,
          90,
          89,
          90,
          91,
          92,
          92,
          92,
          92,
          93,
          94,
          94,
          93,
          91,
          90,
          90,
          91
        ],
        "nitrogen_dioxide": [
          0.2,
          0.3,
          0.5,
          0.8,
          1.3,
          1.8,
          2.2,
          2.3,
          2.3,
          2.3,
          2.2,
          2.1,
          2,
          1.9,
          1.8,
          1.7,
          1.5,
          1.2,
          0.9,
          0.6,
          0.4,
          0.2,
          0.1,
          0.1
        ],
        "carbon_dioxide": [
          436,
          436,
          436,
          436,
          437,
          437,
          438,
          438,
          438,
          438,
          439,
          439,
          440,
          440,
          440,
          439,
          438,
          437,
          436,
          436,
          436,
          436,
          436,
          436
        ],
        "wind_speed_10m": [
          14.1,
          12.4,
          9.8,
          8,
          5.8,
          5,
          7.4,
          7,
          6.9,
          7.4,
          6.1,
          3.9,
          1.8,
          2.2,
          9.7,
          5.2,
          8.8,
          7.8,
          2.5,
          7.9,
          8.1,
          11.1,
          12.3,
          11.8
        ],
        "wind_direction_10m": [
          142,
          144,
          144,
          144,
          150,
          159,
          157,
          168,
          186,
          194,
          208,
          202,
          191,
          180,
          309,
          34,
          351,
          347,
          45,
          141,
          148,
          144,
          142,
          142
        ]
      },
      "hourly_units": {
        "time": "iso8601",
        "sulphur_dioxide": "μg/m³",
        "carbon_monoxide": "μg/m³",
        "nitrogen_dioxide": "μg/m³",
        "carbon_dioxide": "ppm",
        "wind_speed_10m": "km/h",
        "wind_direction_10m": "°"
      }
    },
    {
      "name": "Villarrica",
      "latitude": -39.42,
      "longitude": -71.93,
      "hourly": {
        "time": [
          "2025-10-09T00:00",
          "2025-10-09T01:00",
          "2025-10-09T02:00",
          "2025-10-09T03:00",
          "2025-10-09T04:00",
          "2025-10-09T05:00",
          "2025-10-09T06:00",
          "2025-10-09T07:00",
          "2025-10-09T08:00",
          "2025-10-09T09:00",
          "2025-10-09T10:00",
          "2025-10-09T11:00",
          "2025-10-09T12:00",
          "2025-10-09T13:00",
          "2025-10-09T14:00",
          "2025-10-09T15:00",
          "2025-10-09T16:00",
          "2025-10-09T17:00",
          "2025-10-09T18:00",
          "2025-10-09T19:00",
          "2025-10-09T20:00",
          "2025-10-09T21:00",
          "2025-10-09T22:00",
          "2025-10-09T23:00"
        ],
        "sulphur_dioxide": [
          0.2,
          0.2,
          0.2,
          0.2,
          0.1,
          0.1,
          0,
          0,
          0,
          0,
          0,
          0,
          0,
          0,
          0.1,
          0.1,
          0.1,
          0.1,
          0.1,
          0.1,
          0.1,
          0.1,
          0.1,
          0.2
        ],
        "carbon_monoxide": [
          111,
          111,
          110,
          108,
          107,
          105,
          103,
          101,
          98,
          95,
          92,
          88,
          86,
          85,
          86,
          86,
          87,
          87,
          88,
          88,
          89,
          89,
          89,
          89
        ],
        "nitrogen_dioxide": [
          2.4,
          2.7,
          3.1,
          3.2,
          2.9,
          2.3,
          1.9,
          1.7,
          1.7,
          1.6,
          1.4,
          1.1,
          0.9,
          0.7,
          0.5,
          0.4,
          0.4,
          0.4,
          0.5,
          0.5,
          0.6,
          0.8,
          1.4,
          2.1
        ],
        "carbon_dioxide": [
          422,
          424,
          427,
          430,
          432,
          434,
          436,
          438,
          439,
          440,
          439,
          437,
          435,
          435,
          435,
          435,
          435,
          434,
          433,
          432,
          430,
          430,
          432,
          434
        ],
        "wind_speed_10m": [
          5,
          3.2,
          3.8,
          3.6,
          3.5,
          3.7,
          2.5,
          1.8,
          2.3,
          1.8,
          3.1,
          4.9,
          7.1,
          4.9,
          5.4,
          8.3,
          9.5,
          9.7,
          10.4,
          12.1,
          14,
          9.5,
          9.2,
          6.2
        ],
        "wind_direction_10m": [
          270,
          297,
          311,
          315,
          294,
          281,
          262,
          281,
          309,
          349,
          36,
          54,
          49,
          36,
          352,
          342,
          331,
          333,
          314,
          293,
          282,
          279,
          281,
          291
        ]
      },
      "hourly_units": {
        "time": "iso8601",
        "sulphur_dioxide": "μg/m³",
        "carbon_monoxide": "μg/m³",
        "nitrogen_dioxide": "μg/m³",
        "carbon_dioxide": "ppm",
        "wind_speed_10m": "km/h",
        "wind_direction_10m": "°"
      }
    },
    {
      "name": "Poás",
      "latitude": 10.19751,
      "longitude": -84.23084,
      "hourly": {
        "time": [
          "2025-10-09T00:00",
          "2025-10-09T01:00",
          "2025-10-09T02:00",
          "2025-10-09T03:00",
          "2025-10-09T04:00",
          "2025-10-09T05:00",
          "2025-10-09T06:00",
          "2025-10-09T07:00",
          "2025-10-09T08:00",
          "2025-10-09T09:00",
          "2025-10-09T10:00",
          "2025-10-09T11:00",
          "2025-10-09T12:00",
          "2025-10-09T13:00",
          "2025-10-09T14:00",
          "2025-10-09T15:00",
          "2025-10-09T16:00",
          "2025-10-09T17:00",
          "2025-10-09T18:00",
          "2025-10-09T19:00",
          "2025-10-09T20:00",
          "2025-10-09T21:00",
          "2025-10-09T22:00",
          "2025-10-09T23:00"
        ],
        "sulphur_dioxide": [
          3.8,
          3.7,
          3.5,
          3.3,
          3,
          2.7,
          2.5,
          2.5,
          2.5,
          2.6,
          2.7,
          2.7,
          2.9,
          3.2,
          3.7,
          4.1,
          4.6,
          5.1,
          5.3,
          4.8,
          4,
          3.3,
          3.1,
          3
        ],
        "carbon_monoxide": [
          207,
          228,
          248,
          255,
          239,
          210,
          184,
          167,
          153,
          144,
          142,
          144,
          144,
          136,
          126,
          118,
          116,
          118,
          120,
          121,
          122,
          128,
          144,
          166
        ],
        "nitrogen_dioxide": [
          13.8,
          14.7,
          16,
          17,
          17.4,
          17.5,
          17.6,
          17.7,
          17.6,
          17.5,
          17.6,
          17.7,
          16.4,
          12.5,
          7.3,
          3.4,
          1.9,
          1.8,
          2.1,
          2.6,
          3.6,
          5.4,
          8.4,
          12.2
        ],
        "carbon_dioxide": [
          437,
          446,
          458,
          466,
          469,
          469,
          468,
          467,
          466,
          464,
          461,
          456,
          451,
          443,
          435,
          428,
          425,
          425,
          425,
          424,
          423,
          424,
          430,
          438
        ],
        "wind_speed_10m": [
          0.4,
          1.5,
          3.6,
          4.1,
          2.5,
          2.2,
          4.6,
          5.3,
          5.9,
          6.1,
          6.1,
          6.5,
          5.1,
          4.5,
          2.5,
          2.6,
          2.6,
          0.7,
          2.9,
          5.2,
          2.5,
          2.9,
          1.6,
          1.1
        ],
        "wind_direction_10m": [
          360,
          135,
          180,
          195,
          188,
          99,
          51,
          28,
          14,
          360,
          360,
          6,
          8,
          14,
          45,
          56,
          74,
          90,
          270,
          282,
          315,
          7,
          27,
          288
        ]
      },
      "hourly_units": {
        "time": "iso8601",
        "sulphur_dioxide": "μg/m³",
        "carbon_monoxide": "μg/m³",
        "nitrogen_dioxide": "μg/m³",
        "carbon_dioxide": "ppm",
        "wind_speed_10m": "km/h",
        "wind_direction_10m": "°"
      }
    },
    {
      "name": "Etna",
      "latitude": 37.751,
      "longitude": 14.9934,
      "hourly": {
        "time": [
          "2025-10-09T00:00",
          "2025-10-09T01:00",
          "2025-10-09T02:00",
          "2025-10-09T03:00",
          "2025-10-09T04:00",
          "2025-10-09T05:00",
          "2025-10-09T06:00",
          "2025-10-09T07:00",
          "2025-10-09T08:00",
          "2025-10-09T09:00",
          "2025-10-09T10:00",
          "2025-10-09T11:00",
          "2025-10-09T12:00",
          "2025-10-09T13:00",
          "2025-10-09T14:00",
          "2025-10-09T15:00",
          "2025-10-09T16:00",
          "2025-10-09T17:00",
          "2025-10-09T18:00",
          "2025-10-09T19:00",
          "2025-10-09T20:00",
          "2025-10-09T21:00",
          "2025-10-09T22:00",
          "2025-10-09T23:00"
        ],
        "sulphur_dioxide": [
          0.1,
          0.1,
          0.1,
          0.1,
          0.1,
          0.1,
          0.1,
          0.1,
          0.1,
          0.1,
          0.1,
          0.2,
          0.2,
          0.2,
          0.2,
          0.2,
          0.3,
          0.4,
          0.4,
          0.4,
          0.5,
          0.6,
          0.7,
          0.6
        ],
        "carbon_monoxide": [
          108,
          107,
          108,
          108,
          108,
          108,
          107,
          112,
          113,
          113,
          115,
          115,
          115,
          114,
          113,
          113,
          111,
          113,
          121,
          123,
          125,
          122,
          116,
          114
        ],
        "nitrogen_dioxide": [
          0.3,
          0.3,
          0.4,
          0.4,
          0.4,
          0.5,
          0.6,
          0.7,
          0.7,
          0.7,
          0.7,
          0.7,
          0.6,
          0.6,
          0.6,
          0.8,
          1.5,
          2.6,
          2.9,
          2.9,
          2.8,
          2.1,
          1.6,
          1.3
        ],
        "carbon_dioxide": [
          445,
          444,
          444,
          443,
          443,
          444,
          443,
          441,
          437,
          435,
          434,
          435,
          435,
          435,
          434,
          435,
          438,
          443,
          447,
          449,
          451,
          451,
          450,
          448
        ],
        "wind_speed_10m": [
          14.1,
          12.6,
          10.1,
          11.5,
          11.8,
          9.8,
          12.1,
          11.5,
          9.6,
          10.2,
          10.2,
          8.7,
          10.8,
          12.2,
          13,
          12.1,
          11.4,
          8.6,
          6.2,
          5,
          5.9,
          6.3,
          5.4,
          5.4
        ],
        "wind_direction_10m": [
          345,
          340,
          325,
          328,
          329,
          324,
          330,
          328,
          326,
          321,
          312,
          308,
          296,
          284,
          273,
          280,
          281,
          292,
          291,
          300,
          308,
          294,
          290,
          290
        ]
      },
      "hourly_units": {
        "time": "iso8601",
        "sulphur_dioxide": "μg/m³",
        "carbon_monoxide": "μg/m³",
        "nitrogen_dioxide": "μg/m³",
        "carbon_dioxide": "ppm",
        "wind_speed_10m": "km/h",
        "wind_direction_10m": "°"
      }
    },
    {
      "name": "Stromboli",
      "latitude": 38.789,
      "longitude": 15.213,
      "hourly": {
        "time": [
          "2025-10-09T00:00",
          "2025-10-09T01:00",
          "2025-10-09T02:00",
          "2025-10-09T03:00",
          "2025-10-09T04:00",
          "2025-10-09T05:00",
          "2025-10-09T06:00",
          "2025-10-09T07:00",
          "2025-10-09T08:00",
          "2025-10-09T09:00",
          "2025-10-09T10:00",
          "2025-10-09T11:00",
          "2025-10-09T12:00",
          "2025-10-09T13:00",
          "2025-10-09T14:00",
          "2025-10-09T15:00",
          "2025-10-09T16:00",
          "2025-10-09T17:00",
          "2025-10-09T18:00",
          "2025-10-09T19:00",
          "2025-10-09T20:00",
          "2025-10-09T21:00",
          "2025-10-09T22:00",
          "2025-10-09T23:00"
        ],
        "sulphur_dioxide": [
          0.3,
          0.3,
          0.2,
          0.2,
          0.3,
          0.3,
          0.3,
          0.3,
          0.3,
          0.3,
          0.4,
          0.4,
          0.4,
          0.4,
          0.4,
          0.5,
          0.5,
          0.5,
          0.5,
          0.5,
          0.5,
          0.4,
          0.4,
          0.4
        ],
        "carbon_monoxide": [
          140,
          138,
          135,
          136,
          136,
          136,
          136,
          137,
          137,
          136,
          135,
          133,
          130,
          129,
          128,
          128,
          129,
          130,
          130,
          130,
          131,
          131,
          131,
          131
        ],
        "nitrogen_dioxide": [
          1.2,
          1.2,
          1.3,
          1.3,
          1.4,
          1.6,
          1.8,
          1.9,
          1.6,
          1.5,
          1.3,
          1.1,
          1,
          1,
          1,
          1.3,
          1.7,
          2.1,
          2.1,
          2.1,
          2.1,
          2,
          1.8,
          1.6
        ],
        "carbon_dioxide": [
          433,
          433,
          434,
          435,
          435,
          435,
          435,
          435,
          435,
          435,
          435,
          435,
          435,
          435,
          435,
          435,
          435,
          435,
          435,
          435,
          435,
          435,
          435,
          435
        ],
        "wind_speed_10m": [
          12.6,
          11.9,
          11.2,
          11.4,
          12.1,
          10.4,
          10.6,
          8.6,
          7.3,
          10.1,
          9.8,
          9.9,
          7.8,
          6.2,
          4.9,
          3.9,
          3.3,
          2.5,
          3.4,
          4.7,
          5.2,
          5.1,
          5.3,
          5.4
        ],
        "wind_direction_10m": [
          329,
          325,
          315,
          294,
          293,
          290,
          294,
          292,
          290,
          297,
          294,
          289,
          283,
          280,
          287,
          304,
          319,
          8,
          58,
          86,
          106,
          129,
          118,
          94
        ]
      },
      "hourly_units": {
        "time": "iso8601",
        "sulphur_dioxide": "μg/m³",
        "carbon_monoxide": "μg/m³",
        "nitrogen_dioxide": "μg/m³",
        "carbon_dioxide": "ppm",
        "wind_speed_10m": "km/h",
        "wind_direction_10m": "°"
      }
    },
    {
      "name": "Aso",
      "latitude": 32.884,
      "longitude": 131.104,
      "hourly": {
        "time": [
          "2025-10-09T00:00",
          "2025-10-09T01:00",
          "2025-10-09T02:00",
          "2025-10-09T03:00",
          "2025-10-09T04:00",
          "2025-10-09T05:00",
          "2025-10-09T06:00",
          "2025-10-09T07:00",
          "2025-10-09T08:00",
          "2025-10-09T09:00",
          "2025-10-09T10:00",
          "2025-10-09T11:00",
          "2025-10-09T12:00",
          "2025-10-09T13:00",
          "2025-10-09T14:00",
          "2025-10-09T15:00",
          "2025-10-09T16:00",
          "2025-10-09T17:00",
          "2025-10-09T18:00",
          "2025-10-09T19:00",
          "2025-10-09T20:00",
          "2025-10-09T21:00",
          "2025-10-09T22:00",
          "2025-10-09T23:00"
        ],
        "sulphur_dioxide": [
          1.8,
          3.1,
          4.9,
          6.6,
          8.1,
          9.4,
          9.7,
          8.1,
          5.5,
          3.5,
          2.8,
          2.8,
          2.8,
          2.7,
          2.7,
          2.6,
          2.5,
          2.4,
          2.2,
          1.8,
          1.2,
          1.1,
          1.5,
          2.3
        ],
        "carbon_monoxide": [
          297,
          281,
          263,
          254,
          258,
          270,
          283,
          293,
          304,
          317,
          342,
          369,
          375,
          339,
          281,
          240,
          231,
          238,
          250,
          270,
          296,
          310,
          300,
          278
        ],
        "nitrogen_dioxide": [
          2.9,
          2.4,
          1.8,
          1.3,
          1,
          0.9,
          1.1,
          1.9,
          3.1,
          4.2,
          5.2,
          6.1,
          6.9,
          7.5,
          8,
          8.2,
          7.9,
          7.2,
          6.6,
          6.3,
          6.1,
          5.8,
          5.2,
          4.4
        ],
        "carbon_dioxide": [
          439,
          437,
          436,
          435,
          434,
          433,
          433,
          433,
          434,
          436,
          439,
          442,
          445,
          446,
          446,
          446,
          448,
          450,
          452,
          455,
          457,
          457,
          452,
          444
        ],
        "wind_speed_10m": [
          15.6,
          16.6,
          16.8,
          11.1,
          12.4,
          13,
          11.6,
          13.2,
          14.1,
          13,
          13.6,
          13.3,
          13.3,
          13.8,
          14.3,
          13.8,
          13.7,
          13,
          12.6,
          12.2,
          11.5,
          10.8,
          10.5,
          10.6
        ],
        "wind_direction_10m": [
          61,
          60,
          59,
          54,
          60,
          66,
          60,
          68,
          71,
          71,
          68,
          71,
          71,
          75,
          80,
          84,
          85,
          87,
          85,
          88,
          94,
          94,
          96,
          100
        ]
      },
      "hourly_units": {
        "time": "iso8601",
        "sulphur_dioxide": "μg/m³",
        "carbon_monoxide": "μg/m³",
        "nitrogen_dioxide": "μg/m³",
        "carbon_dioxide": "ppm",
        "wind_speed_10m": "km/h",
        "wind_direction_10m": "°"
      }
    },
    {
      "name": "Sakurajima",
      "latitude": 31.585,
      "longitude": 130.657,
      "hourly": {
        "time": [
          "2025-10-09T00:00",
          "2025-10-09T01:00",
          "2025-10-09T02:00",
          "2025-10-09T03:00",
          "2025-10-09T04:00",
          "2025-10-09T05:00",
          "2025-10-09T06:00",
          "2025-10-09T07:00",
          "2025-10-09T08:00",
          "2025-10-09T09:00",
          "2025-10-09T10:00",
          "2025-10-09T11:00",
          "2025-10-09T12:00",
          "2025-10-09T13:00",
          "2025-10-09T14:00",
          "2025-10-09T15:00",
          "2025-10-09T16:00",
          "2025-10-09T17:00",
          "2025-10-09T18:00",
          "2025-10-09T19:00",
          "2025-10-09T20:00",
          "2025-10-09T21:00",
          "2025-10-09T22:00",
          "2025-10-09T23:00"
        ],
        "sulphur_dioxide": [
          3,
          8.8,
          16.8,
          22.3,
          23,
          21.2,
          19.2,
          17.7,
          16,
          14.3,
          12.5,
          10.7,
          8.9,
          7,
          5.1,
          3.7,
          2.9,
          2.6,
          2.3,
          2.1,
          1.9,
          1.8,
          1.4,
          0.9
        ],
        "carbon_monoxide": [
          263,
          256,
          245,
          236,
          233,
          233,
          232,
          229,
          226,
          220,
          211,
          201,
          190,
          178,
          166,
          157,
          154,
          156,
          157,
          158,
          159,
          159,
          159,
          158
        ],
        "nitrogen_dioxide": [
          3.6,
          2.8,
          1.7,
          0.9,
          0.5,
          0.5,
          1.2,
          3.4,
          6.4,
          8.5,
          9,
          8.6,
          8.2,
          8.2,
          8.2,
          8.1,
          7.6,
          7,
          6.6,
          6.6,
          6.8,
          6.6,
          5.9,
          4.8
        ],
        "carbon_dioxide": [
          486,
          476,
          466,
          458,
          453,
          451,
          449,
          448,
          448,
          448,
          447,
          447,
          446,
          445,
          444,
          444,
          444,
          445,
          447,
          450,
          454,
          456,
          455,
          451
        ],
        "wind_speed_10m": [
          6.1,
          4.5,
          3.3,
          2.2,
          4.1,
          5.6,
          12.9,
          10.8,
          7.2,
          9.2,
          10.9,
          11.4,
          13.1,
          15.2,
          17.5,
          16.9,
          16.4,
          15.7,
          14.6,
          14.1,
          14.6,
          14.5,
          16.7,
          17.2
        ],
        "wind_direction_10m": [
          50,
          29,
          354,
          270,
          165,
          220,
          234,
          195,
          153,
          121,
          117,
          101,
          99,
          94,
          82,
          78,
          71,
          70,
          70,
          71,
          74,
          71,
          76,
          74
        ]
      },
      "hourly_units": {
        "time": "iso8601",
        "sulphur_dioxide": "μg/m³",
        "carbon_monoxide": "μg/m³",
        "nitrogen_dioxide": "μg/m³",
        "carbon_dioxide": "ppm",
        "wind_speed_10m": "km/h",
        "wind_direction_10m": "°"
      }
    },
    {
      "name": "Semeru",
      "latitude": -8.108,
      "longitude": 112.922,
      "hourly": {
        "time": [
          "2025-10-09T00:00",
          "2025-10-09T01:00",
          "2025-10-09T02:00",
          "2025-10-09T03:00",
          "2025-10-09T04:00",
          "2025-10-09T05:00",
          "2025-10-09T06:00",
          "2025-10-09T07:00",
          "2025-10-09T08:00",
          "2025-10-09T09:00",
          "2025-10-09T10:00",
          "2025-10-09T11:00",
          "2025-10-09T12:00",
          "2025-10-09T13:00",
          "2025-10-09T14:00",
          "2025-10-09T15:00",
          "2025-10-09T16:00",
          "2025-10-09T17:00",
          "2025-10-09T18:00",
          "2025-10-09T19:00",
          "2025-10-09T20:00",
          "2025-10-09T21:00",
          "2025-10-09T22:00",
          "2025-10-09T23:00"
        ],
        "sulphur_dioxide": [
          3.4,
          3.5,
          3.6,
          3.7,
          3.9,
          4.2,
          4.5,
          4.8,
          5.1,
          5.4,
          5.9,
          6.3,
          6.6,
          6.5,
          6.2,
          5.8,
          5.3,
          4.7,
          4.3,
          4.1,
          4,
          4.2,
          5,
          6
        ],
        "carbon_monoxide": [
          216,
          214,
          212,
          214,
          224,
          238,
          249,
          248,
          244,
          250,
          279,
          319,
          347,
          359,
          361,
          344,
          293,
          225,
          180,
          184,
          211,
          228,
          217,
          195
        ],
        "nitrogen_dioxide": [
          5.7,
          4.5,
          2.9,
          1.7,
          1.3,
          1.4,
          1.7,
          1.5,
          1.5,
          3.3,
          8.7,
          15.8,
          20.9,
          21.9,
          20.8,
          19.5,
          18.3,
          16.8,
          15.8,
          15.9,
          16.5,
          16,
          13.3,
          9.6
        ],
        "carbon_dioxide": [
          434,
          432,
          434,
          436,
          437,
          437,
          437,
          435,
          433,
          434,
          442,
          454,
          464,
          470,
          473,
          474,
          470,
          463,
          459,
          460,
          464,
          464,
          456,
          444
        ],
        "wind_speed_10m": [
          3.4,
          7.6,
          10.4,
          11.9,
          13.4,
          14.1,
          14.3,
          13.5,
          11.2,
          9.6,
          8.9,
          5.8,
          5.6,
          6.1,
          5.2,
          4.2,
          3.8,
          4.1,
          4.3,
          3.3,
          3.6,
          3.7,
          3.9,
          3.7
        ],
        "wind_direction_10m": [
          148,
          180,
          182,
          182,
          185,
          186,
          170,
          171,
          176,
          167,
          159,
          173,
          165,
          140,
          155,
          160,
          139,
          135,
          132,
          139,
          143,
          119,
          112,
          101
        ]
      },
      "hourly_units": {
        "time": "iso8601",
        "sulphur_dioxide": "μg/m³",
        "carbon_monoxide": "μg/m³",
        "nitrogen_dioxide": "μg/m³",
        "carbon_dioxide": "ppm",
        "wind_speed_10m": "km/h",
        "wind_direction_10m": "°"
      }
    },
    {
      "name": "Lewotolo",
      "latitude": -8.272,
      "longitude": 123.505,
      "hourly": {
        "time": [
          "2025-10-09T00:00",
          "2025-10-09T01:00",
          "2025-10-09T02:00",
          "2025-10-09T03:00",
          "2025-10-09T04:00",
          "2025-10-09T05:00",
          "2025-10-09T06:00",
          "2025-10-09T07:00",
          "2025-10-09T08:00",
          "2025-10-09T09:00",
          "2025-10-09T10:00",
          "2025-10-09T11:00",
          "2025-10-09T12:00",
          "2025-10-09T13:00",
          "2025-10-09T14:00",
          "2025-10-09T15:00",
          "2025-10-09T16:00",
          "2025-10-09T17:00",
          "2025-10-09T18:00",
          "2025-10-09T19:00",
          "2025-10-09T20:00",
          "2025-10-09T21:00",
          "2025-10-09T22:00",
          "2025-10-09T23:00"
        ],
        "sulphur_dioxide": [
          1.2,
          1.3,
          1.3,
          1.4,
          1.5,
          1.5,
          1.6,
          1.7,
          1.9,
          1.9,
          1.7,
          1.4,
          1.2,
          1.2,
          1.3,
          1.4,
          1.5,
          1.5,
          1.5,
          1.4,
          1.3,
          1.2,
          1.2,
          1.2
        ],
        "carbon_monoxide": [
          269,
          364,
          530,
          695,
          876,
          1055,
          1106,
          922,
          610,
          367,
          272,
          246,
          253,
          296,
          373,
          434,
          458,
          466,
          480,
          522,
          569,
          569,
          478,
          339
        ],
        "nitrogen_dioxide": [
          1.4,
          1.3,
          1.1,
          1,
          1.1,
          1.2,
          1.4,
          1.7,
          2,
          2.1,
          1.9,
          1.5,
          1.3,
          1.3,
          1.5,
          1.6,
          1.6,
          1.6,
          1.6,
          1.6,
          1.7,
          1.7,
          1.7,
          1.8
        ],
        "carbon_dioxide": [
          446,
          443,
          447,
          450,
          451,
          452,
          452,
          450,
          447,
          446,
          446,
          447,
          451,
          458,
          468,
          478,
          488,
          498,
          506,
          512,
          515,
          510,
          491,
          465
        ],
        "wind_speed_10m": [
          5.9,
          3.1,
          2.4,
          8,
          12.7,
          14.1,
          13.8,
          12.6,
          11.9,
          10.9,
          7.3,
          5.6,
          5.4,
          4.6,
          4.8,
          5.4,
          6.5,
          7.3,
          5.4,
          4.2,
          5.9,
          7.3,
          7.9,
          7
        ],
        "wind_direction_10m": [
          194,
          201,
          333,
          350,
          352,
          4,
          9,
          13,
          29,
          44,
          57,
          75,
          94,
          135,
          153,
          172,
          199,
          200,
          184,
          200,
          194,
          191,
          196,
          192
        ]
      },
      "hourly_units": {
        "time": "iso8601",
        "sulphur_dioxide": "μg/m³",
        "carbon_monoxide": "μg/m³",
        "nitrogen_dioxide": "μg/m³",
        "carbon_dioxide": "ppm",
        "wind_speed_10m": "km/h",
        "wind_direction_10m": "°"
      }
    },
    {
      "name": "Ibu",
      "latitude": 1.488,
      "longitude": 127.63,
      "hourly": {
        "time": [
          "2025-10-09T00:00",
          "2025-10-09T01:00",
          "2025-10-09T02:00",
          "2025-10-09T03:00",
          "2025-10-09T04:00",
          "2025-10-09T05:00",
          "2025-10-09T06:00",
          "2025-10-09T07:00",
          "2025-10-09T08:00",
          "2025-10-09T09:00",
          "2025-10-09T10:00",
          "2025-10-09T11:00",
          "2025-10-09T12:00",
          "2025-10-09T13:00",
          "2025-10-09T14:00",
          "2025-10-09T15:00",
          "2025-10-09T16:00",
          "2025-10-09T17:00",
          "2025-10-09T18:00",
          "2025-10-09T19:00",
          "2025-10-09T20:00",
          "2025-10-09T21:00",
          "2025-10-09T22:00",
          "2025-10-09T23:00"
        ],
        "sulphur_dioxide": [
          0.5,
          0.4,
          0.4,
          0.3,
          0.3,
          0.3,
          0.3,
          0.3,
          0.3,
          0.4,
          0.5,
          0.6,
          0.7,
          0.7,
          0.7,
          0.6,
          0.5,
          0.5,
          0.4,
          0.4,
          0.3,
          0.4,
          0.2,
          0.1
        ],
        "carbon_monoxide": [
          121,
          118,
          115,
          114,
          113,
          114,
          117,
          125,
          135,
          142,
          144,
          143,
          140,
          134,
          125,
          119,
          118,
          119,
          121,
          122,
          124,
          124,
          122,
          118
        ],
        "nitrogen_dioxide": [
          0.3,
          0.2,
          0.2,
          0.1,
          0.1,
          0.1,
          0.1,
          0.2,
          0.3,
          0.5,
          0.7,
          0.9,
          1,
          1.1,
          1.1,
          1.2,
          1.3,
          1.5,
          1.6,
          1.8,
          2,
          2,
          1.6,
          0.9
        ],
        "carbon_dioxide": [
          434,
          426,
          430,
          433,
          431,
          429,
          428,
          429,
          433,
          438,
          448,
          460,
          469,
          472,
          472,
          474,
          479,
          486,
          493,
          504,
          517,
          517,
          495,
          462
        ],
        "wind_speed_10m": [
          3.1,
          3.3,
          4.9,
          8.4,
          10.4,
          12,
          8.2,
          6.1,
          4.1,
          1.8,
          3.5,
          4.7,
          6,
          5.9,
          5.7,
          5.6,
          5.5,
          5.4,
          5.6,
          5.2,
          5.1,
          5.2,
          5.2,
          4.8
        ],
        "wind_direction_10m": [
          159,
          174,
          197,
          211,
          226,
          237,
          232,
          230,
          218,
          169,
          114,
          113,
          107,
          104,
          108,
          117,
          113,
          110,
          105,
          102,
          98,
          106,
          102,
          103
        ]
      },
      "hourly_units": {
        "time": "iso8601",
        "sulphur_dioxide": "μg/m³",
        "carbon_monoxide": "μg/m³",
        "nitrogen_dioxide": "μg/m³",
        "carbon_dioxide": "ppm",
        "wind_speed_10m": "km/h",
        "wind_direction_10m": "°"
      }
    },
    {
      "name": "Dukono",
      "latitude": 1.693,
      "longitude": 127.878,
      "hourly": {
        "time": [
          "2025-10-09T00:00",
          "2025-10-09T01:00",
          "2025-10-09T02:00",
          "2025-10-09T03:00",
          "2025-10-09T04:00",
          "2025-10-09T05:00",
          "2025-10-09T06:00",
          "2025-10-09T07:00",
          "2025-10-09T08:00",
          "2025-10-09T09:00",
          "2025-10-09T10:00",
          "2025-10-09T11:00",
          "2025-10-09T12:00",
          "2025-10-09T13:00",
          "2025-10-09T14:00",
          "2025-10-09T15:00",
          "2025-10-09T16:00",
          "2025-10-09T17:00",
          "2025-10-09T18:00",
          "2025-10-09T19:00",
          "2025-10-09T20:00",
          "2025-10-09T21:00",
          "2025-10-09T22:00",
          "2025-10-09T23:00"
        ],
        "sulphur_dioxide": [
          0.3,
          0.3,
          0.3,
          0.3,
          0.5,
          0.7,
          0.9,
          0.9,
          0.9,
          0.9,
          0.9,
          0.9,
          0.8,
          0.6,
          0.4,
          0.3,
          0.3,
          0.4,
          0.4,
          0.3,
          0.2,
          0.2,
          0,
          0
        ],
        "carbon_monoxide": [
          112,
          111,
          112,
          112,
          111,
          110,
          109,
          109,
          110,
          114,
          124,
          138,
          146,
          145,
          138,
          132,
          127,
          121,
          119,
          122,
          129,
          131,
          125,
          115
        ],
        "nitrogen_dioxide": [
          0.2,
          0.2,
          0.1,
          0.1,
          0.1,
          0.1,
          0.1,
          0.2,
          0.3,
          0.4,
          0.5,
          0.6,
          0.7,
          0.8,
          0.9,
          1,
          1.1,
          1.2,
          1.4,
          1.7,
          2,
          2,
          1.5,
          0.8
        ],
        "carbon_dioxide": [
          435,
          429,
          429,
          430,
          428,
          426,
          425,
          425,
          427,
          434,
          451,
          474,
          491,
          498,
          500,
          500,
          499,
          497,
          495,
          497,
          499,
          495,
          477,
          453
        ],
        "wind_speed_10m": [
          3.1,
          3.3,
          4.9,
          8.4,
          10.4,
          12,
          8.2,
          6.1,
          4.1,
          1.8,
          3.5,
          4.7,
          6,
          5.9,
          5.7,
          5.6,
          5.5,
          5.4,
          5.6,
          5.2,
          5.1,
          5.2,
          5.2,
          4.8
        ],
        "wind_direction_10m": [
          159,
          174,
          197,
          211,
          226,
          237,
          232,
          230,
          218,
          169,
          114,
          113,
          107,
          104,
          108,
          117,
          113,
          110,
          105,
          102,
          98,
          106,
          102,
          103
        ]
      },
      "hourly_units": {
        "time": "iso8601",
        "sulphur_dioxide": "μg/m³",
        "carbon_monoxide": "μg/m³",
        "nitrogen_dioxide": "μg/m³",
        "carbon_dioxide": "ppm",
        "wind_speed_10m": "km/h",
        "wind_direction_10m": "°"
      }
    },
    {
      "name": "Krakatau",
      "latitude": -6.1024,
      "longitude": 105.4231,
      "hourly": {
        "time": [
          "2025-10-09T00:00",
          "2025-10-09T01:00",
          "2025-10-09T02:00",
          "2025-10-09T03:00",
          "2025-10-09T04:00",
          "2025-10-09T05:00",
          "2025-10-09T06:00",
          "2025-10-09T07:00",
          "2025-10-09T08:00",
          "2025-10-09T09:00",
          "2025-10-09T10:00",
          "2025-10-09T11:00",
          "2025-10-09T12:00",
          "2025-10-09T13:00",
          "2025-10-09T14:00",
          "2025-10-09T15:00",
          "2025-10-09T16:00",
          "2025-10-09T17:00",
          "2025-10-09T18:00",
          "2025-10-09T19:00",
          "2025-10-09T20:00",
          "2025-10-09T21:00",
          "2025-10-09T22:00",
          "2025-10-09T23:00"
        ],
        "sulphur_dioxide": [
          48.3,
          56.1,
          66.8,
          75,
          78.9,
          80.3,
          79.2,
          74.4,
          67.1,
          61.1,
          58.9,
          58,
          55.2,
          47.3,
          37.5,
          32.4,
          36.4,
          45.1,
          52.3,
          54.5,
          55.3,
          59,
          68.5,
          80.9
        ],
        "carbon_monoxide": [
          235,
          270,
          315,
          348,
          361,
          363,
          357,
          344,
          324,
          295,
          251,
          199,
          160,
          143,
          140,
          139,
          141,
          145,
          148,
          138,
          125,
          137,
          198,
          283
        ],
        "nitrogen_dioxide": [
          15.5,
          14.3,
          12.6,
          10.6,
          8.1,
          5.4,
          3.4,
          2.7,
          2.8,
          3.1,
          3.4,
          3.8,
          4.1,
          4.2,
          4.1,
          4.4,
          5.2,
          6.2,
          7.1,
          7.5,
          7.8,
          8.4,
          10,
          11.9
        ],
        "carbon_dioxide": [
          451,
          452,
          453,
          453,
          453,
          453,
          452,
          452,
          451,
          450,
          447,
          444,
          441,
          440,
          441,
          441,
          441,
          441,
          441,
          440,
          439,
          440,
          446,
          455
        ],
        "wind_speed_10m": [
          16.3,
          14.1,
          12.2,
          8.9,
          6.8,
          5.1,
          7.2,
          9,
          11.2,
          12.2,
          12.7,
          14.8,
          17.1,
          17.4,
          17.4,
          15.5,
          14.7,
          14.9,
          14.4,
          13.7,
          14.3,
          14.6,
          14.8,
          13.5
        ],
        "wind_direction_10m": [
          133,
          128,
          124,
          122,
          122,
          135,
          174,
          185,
          184,
          180,
          173,
          166,
          158,
          153,
          153,
          152,
          149,
          148,
          148,
          150,
          146,
          142,
          135,
          132
        ]
      },
      "hourly_units": {
        "time": "iso8601",
        "sulphur_dioxide": "μg/m³",
        "carbon_monoxide": "μg/m³",
        "nitrogen_dioxide": "μg/m³",
        "carbon_dioxide": "ppm",
        "wind_speed_10m": "km/h",
        "wind_direction_10m": "°"
      }
    },
    {
      "name": "Nyiragongo",
      "latitude": -1.52,
      "longitude": 29.25,
      "hourly": {
        "time": [
          "2025-10-09T00:00",
          "2025-10-09T01:00",
          "2025-10-09T02:00",
          "2025-10-09T03:00",
          "2025-10-09T04:00",
          "2025-10-09T05:00",
          "2025-10-09T06:00",
          "2025-10-09T07:00",
          "2025-10-09T08:00",
          "2025-10-09T09:00",
          "2025-10-09T10:00",
          "2025-10-09T11:00",
          "2025-10-09T12:00",
          "2025-10-09T13:00",
          "2025-10-09T14:00",
          "2025-10-09T15:00",
          "2025-10-09T16:00",
          "2025-10-09T17:00",
          "2025-10-09T18:00",
          "2025-10-09T19:00",
          "2025-10-09T20:00",
          "2025-10-09T21:00",
          "2025-10-09T22:00",
          "2025-10-09T23:00"
        ],
        "sulphur_dioxide": [
          2.2,
          1.8,
          1.3,
          1,
          1.1,
          1.4,
          1.6,
          1.4,
          1,
          1,
          1.9,
          3.1,
          3.9,
          3.7,
          3.1,
          2.6,
          2.7,
          3.1,
          3.1,
          2.4,
          1.5,
          0.7,
          0.4,
          0.3
        ],
        "carbon_monoxide": [
          302,
          272,
          247,
          228,
          216,
          210,
          201,
          185,
          167,
          155,
          152,
          155,
          159,
          160,
          161,
          174,
          208,
          254,
          288,
          304,
          309,
          301,
          270,
          225
        ],
        "nitrogen_dioxide": [
          5.3,
          6.2,
          7.4,
          7.7,
          6.1,
          3.6,
          1.6,
          0.8,
          0.6,
          0.5,
          0.4,
          0.3,
          0.4,
          0.4,
          0.4,
          1,
          2.6,
          4.6,
          6.3,
          7.3,
          7.9,
          8,
          7.1,
          5.7
        ],
        "carbon_dioxide": [
          487,
          486,
          484,
          478,
          462,
          442,
          427,
          424,
          427,
          430,
          431,
          431,
          431,
          427,
          422,
          422,
          432,
          446,
          458,
          464,
          468,
          470,
          471,
          470
        ],
        "wind_speed_10m": [
          3.7,
          4.8,
          5.6,
          5.2,
          4.9,
          3.8,
          1.8,
          7.4,
          7.1,
          3.8,
          2,
          5.7,
          4.7,
          0.8,
          3,
          3.1,
          2.2,
          1.9,
          1.3,
          1.9,
          3.4,
          4.1,
          6.1,
          6.1
        ],
        "wind_direction_10m": [
          349,
          347,
          27,
          34,
          36,
          49,
          191,
          151,
          139,
          163,
          225,
          235,
          261,
          297,
          166,
          159,
          171,
          158,
          124,
          68,
          58,
          52,
          50,
          45
        ]
      },
      "hourly_units": {
        "time": "iso8601",
        "sulphur_dioxide": "μg/m³",
        "carbon_monoxide": "μg/m³",
        "nitrogen_dioxide": "μg/m³",
        "carbon_dioxide": "ppm",
        "wind_speed_10m": "km/h",
        "wind_direction_10m": "°"
      }
    },
    {
      "name": "Shiveluch",
      "latitude": 56.653,
      "longitude": 161.36,
      "hourly": {
        "time": [
          "2025-10-09T00:00",
          "2025-10-09T01:00",
          "2025-10-09T02:00",
          "2025-10-09T03:00",
          "2025-10-09T04:00",
          "2025-10-09T05:00",
          "2025-10-09T06:00",
          "2025-10-09T07:00",
          "2025-10-09T08:00",
          "2025-10-09T09:00",
          "2025-10-09T10:00",
          "2025-10-09T11:00",
          "2025-10-09T12:00",
          "2025-10-09T13:00",
          "2025-10-09T14:00",
          "2025-10-09T15:00",
          "2025-10-09T16:00",
          "2025-10-09T17:00",
          "2025-10-09T18:00",
          "2025-10-09T19:00",
          "2025-10-09T20:00",
          "2025-10-09T21:00",
          "2025-10-09T22:00",
          "2025-10-09T23:00"
        ],
        "sulphur_dioxide": [
          0.3,
          0.5,
          0.7,
          0.9,
          1,
          1,
          1,
          0.9,
          0.6,
          0.5,
          0.5,
          0.6,
          0.7,
          0.7,
          0.7,
          0.7,
          0.7,
          0.6,
          0.6,
          0.6,
          0.5,
          0.5,
          0.4,
          0.4
        ],
        "carbon_monoxide": [
          135,
          135,
          135,
          135,
          135,
          134,
          134,
          134,
          133,
          133,
          133,
          132,
          132,
          132,
          133,
          133,
          133,
          133,
          133,
          133,
          132,
          132,
          132,
          132
        ],
        "nitrogen_dioxide": [
          0,
          0,
          0,
          0,
          0,
          0.1,
          0.1,
          0.1,
          0.1,
          0.1,
          0.1,
          0.1,
          0.1,
          0.1,
          0.1,
          0.1,
          0.1,
          0,
          0,
          0,
          0,
          0,
          0,
          0
        ],
        "carbon_dioxide": [
          432,
          432,
          432,
          432,
          432,
          432,
          432,
          432,
          432,
          432,
          432,
          433,
          433,
          433,
          432,
          432,
          432,
          433,
          433,
          433,
          433,
          433,
          433,
          432
        ],
        "wind_speed_10m": [
          12.7,
          15.8,
          17.3,
          19.6,
          21.6,
          23.6,
          25.1,
          26.1,
          24,
          22.9,
          22,
          21.5,
          22.1,
          23.2,
          26.3,
          27.6,
          30,
          32,
          34,
          34,
          33.4,
          34.2,
          31.8,
          29.6
        ],
        "wind_direction_10m": [
          135,
          139,
          137,
          131,
          120,
          109,
          111,
          105,
          99,
          97,
          88,
          76,
          68,
          64,
          60,
          59,
          57,
          56,
          54,
          51,
          48,
          49,
          47,
          48
        ]
      },
      "hourly_units": {
        "time": "iso8601",
        "sulphur_dioxide": "μg/m³",
        "carbon_monoxide": "μg/m³",
        "nitrogen_dioxide": "μg/m³",
        "carbon_dioxide": "ppm",
        "wind_speed_10m": "km/h",
        "wind_direction_10m": "°"
      }
    },
    {
      "name": "Ebeko",
      "latitude": 50.686,
      "longitude": 156.014,
      "hourly": {
        "time": [
          "2025-10-09T00:00",
          "2025-10-09T01:00",
          "2025-10-09T02:00",
          "2025-10-09T03:00",
          "2025-10-09T04:00",
          "2025-10-09T05:00",
          "2025-10-09T06:00",
          "2025-10-09T07:00",
          "2025-10-09T08:00",
          "2025-10-09T09:00",
          "2025-10-09T10:00",
          "2025-10-09T11:00",
          "2025-10-09T12:00",
          "2025-10-09T13:00",
          "2025-10-09T14:00",
          "2025-10-09T15:00",
          "2025-10-09T16:00",
          "2025-10-09T17:00",
          "2025-10-09T18:00",
          "2025-10-09T19:00",
          "2025-10-09T20:00",
          "2025-10-09T21:00",
          "2025-10-09T22:00",
          "2025-10-09T23:00"
        ],
        "sulphur_dioxide": [
          0.4,
          0.3,
          0.2,
          0.1,
          0.1,
          0.2,
          0.2,
          0.2,
          0.2,
          0.2,
          0.2,
          0.1,
          0.1,
          0.1,
          0,
          0,
          0,
          0.1,
          0.1,
          0.1,
          0.1,
          0.1,
          0.1,
          0.1
        ],
        "carbon_monoxide": [
          136,
          134,
          129,
          125,
          123,
          123,
          123,
          126,
          129,
          132,
          133,
          132,
          132,
          132,
          132,
          132,
          131,
          130,
          130,
          130,
          131,
          132,
          132,
          133
        ],
        "nitrogen_dioxide": [
          0.2,
          0.2,
          0.2,
          0.2,
          0.2,
          0.1,
          0.1,
          0.1,
          0.1,
          0.1,
          0.1,
          0,
          0,
          0,
          0,
          0,
          0,
          0,
          0,
          0,
          0,
          0,
          0,
          0
        ],
        "carbon_dioxide": [
          436,
          436,
          435,
          434,
          434,
          433,
          433,
          433,
          433,
          433,
          433,
          433,
          433,
          433,
          433,
          433,
          433,
          433,
          433,
          433,
          432,
          432,
          432,
          432
        ],
        "wind_speed_10m": [
          24.1,
          44.8,
          64.5,
          73.5,
          77.8,
          77,
          74.7,
          73,
          72.8,
          73.9,
          75.4,
          75.6,
          75.7,
          74.2,
          74.4,
          72,
          69.8,
          71.1,
          73.6,
          72.3,
          73.2,
          71.3,
          68.1,
          64.7
        ],
        "wind_direction_10m": [
          340,
          5,
          357,
          357,
          350,
          345,
          339,
          336,
          332,
          325,
          317,
          317,
          318,
          318,
          312,
          308,
          305,
          306,
          307,
          308,
          305,
          304,
          304,
          308
        ]
      },
      "hourly_units": {
        "time": "iso8601",
        "sulphur_dioxide": "μg/m³",
        "carbon_monoxide": "μg/m³",
        "nitrogen_dioxide": "μg/m³",
        "carbon_dioxide": "ppm",
        "wind_speed_10m": "km/h",
        "wind_direction_10m": "°"
      }
    },
    {
      "name": "Karymsky",
      "latitude": 54.05,
      "longitude": 159.45,
      "hourly": {
        "time": [
          "2025-10-09T00:00",
          "2025-10-09T01:00",
          "2025-10-09T02:00",
          "2025-10-09T03:00",
          "2025-10-09T04:00",
          "2025-10-09T05:00",
          "2025-10-09T06:00",
          "2025-10-09T07:00",
          "2025-10-09T08:00",
          "2025-10-09T09:00",
          "2025-10-09T10:00",
          "2025-10-09T11:00",
          "2025-10-09T12:00",
          "2025-10-09T13:00",
          "2025-10-09T14:00",
          "2025-10-09T15:00",
          "2025-10-09T16:00",
          "2025-10-09T17:00",
          "2025-10-09T18:00",
          "2025-10-09T19:00",
          "2025-10-09T20:00",
          "2025-10-09T21:00",
          "2025-10-09T22:00",
          "2025-10-09T23:00"
        ],
        "sulphur_dioxide": [
          0.3,
          0.4,
          0.5,
          0.6,
          0.6,
          0.5,
          0.5,
          0.5,
          0.4,
          0.4,
          0.4,
          0.3,
          0.3,
          0.3,
          0.2,
          0.2,
          0.2,
          0.2,
          0.2,
          0.2,
          0.2,
          0.2,
          0.2,
          0.3
        ],
        "carbon_monoxide": [
          137,
          137,
          136,
          135,
          134,
          133,
          132,
          131,
          129,
          128,
          127,
          127,
          127,
          127,
          128,
          128,
          128,
          129,
          129,
          130,
          130,
          131,
          131,
          132
        ],
        "nitrogen_dioxide": [
          0.1,
          0.1,
          0.1,
          0.1,
          0.1,
          0.1,
          0.1,
          0.1,
          0.1,
          0.1,
          0.1,
          0.1,
          0.1,
          0.1,
          0.1,
          0.1,
          0.1,
          0.1,
          0.1,
          0.1,
          0.1,
          0.1,
          0.1,
          0.1
        ],
        "carbon_dioxide": [
          432,
          432,
          432,
          432,
          432,
          433,
          433,
          433,
          434,
          434,
          434,
          434,
          434,
          434,
          434,
          434,
          434,
          434,
          434,
          434,
          434,
          434,
          434,
          433
        ],
        "wind_speed_10m": [
          8.6,
          11.1,
          13.6,
          15.1,
          16.6,
          18.2,
          24.6,
          27.1,
          29.2,
          27.2,
          24.3,
          22.7,
          19.4,
          17.7,
          16.9,
          14.8,
          12.9,
          11.6,
          10.6,
          10.2,
          11.6,
          12,
          13.3,
          16.2
        ],
        "wind_direction_10m": [
          75,
          65,
          68,
          72,
          72,
          63,
          63,
          61,
          55,
          51,
          50,
          47,
          42,
          38,
          34,
          23,
          18,
          22,
          18,
          10,
          355,
          351,
          357,
          359
        ]
      },
      "hourly_units": {
        "time": "iso8601",
        "sulphur_dioxide": "μg/m³",
        "carbon_monoxide": "μg/m³",
        "nitrogen_dioxide": "μg/m³",
        "carbon_dioxide": "ppm",
        "wind_speed_10m": "km/h",
        "wind_direction_10m": "°"
      }
    }
  ]
}