{
  "lastUpdated": "2025-09-24T10:41:10.771Z",
  "volcanoes": [
    {
      "name": "Fuego",
      "latitude": 14.473,
      "longitude": -90.88,
      "hourly": {
        "time": [
          "2025-09-24T00:00",
          "2025-09-24T01:00",
          "2025-09-24T02:00",
          "2025-09-24T03:00",
          "2025-09-24T04:00",
          "2025-09-24T05:00",
          "2025-09-24T06:00",
          "2025-09-24T07:00",
          "2025-09-24T08:00",
          "2025-09-24T09:00",
          "2025-09-24T10:00",
          "2025-09-24T11:00",
          "2025-09-24T12:00",
          "2025-09-24T13:00",
          "2025-09-24T14:00",
          "2025-09-24T15:00",
          "2025-09-24T16:00",
          "2025-09-24T17:00",
          "2025-09-24T18:00",
          "2025-09-24T19:00",
          "2025-09-24T20:00",
          "2025-09-24T21:00",
          "2025-09-24T22:00",
          "2025-09-24T23:00"
        ],
        "sulphur_dioxide": [
          11.6,
          10.5,
          9,
          7.5,
          6.1,
          4.7,
          3.6,
          2.8,
          2.1,
          1.7,
          1.4,
          1.3,
          1.4,
          1.7,
          2.3,
          3.4,
          5.2,
          7.4,
          9.6,
          11.8,
          13.9,
          14.9,
          14.2,
          12.4
        ],
        "carbon_monoxide": [
          443,
          832,
          1328,
          1613,
          1497,
          1170,
          878,
          701,
          560,
          463,
          435,
          451,
          452,
          407,
          347,
          302,
          286,
          285,
          288,
          285,
          286,
          308,
          372,
          457
        ],
        "nitrogen_dioxide": [
          18.4,
          25.7,
          35.7,
          42.9,
          45,
          44.3,
          42.3,
          39.1,
          34.6,
          30.5,
          27.7,
          25.3,
          21.9,
          16.1,
          9.3,
          4.3,
          2.4,
          2.2,
          2.4,
          2,
          1.9,
          3.3,
          6.8,
          11.8
        ],
        "carbon_dioxide": [
          421,
          437,
          458,
          472,
          471,
          463,
          457,
          459,
          464,
          468,
          471,
          472,
          468,
          454,
          436,
          422,
          419,
          421,
          422,
          420,
          418,
          417,
          417,
          418
        ],
        "wind_speed_10m": [
          3.8,
          5.5,
          5.9,
          7.6,
          8.9,
          8.7,
          10.7,
          11.2,
          10.2,
          10.4,
          10.4,
          10.4,
          10.7,
          9.7,
          8.4,
          8.4,
          7.2,
          6.3,
          6.1,
          4,
          7.6,
          5.9,
          4.5,
          4.6
        ],
        "wind_direction_10m": [
          107,
          58,
          43,
          45,
          47,
          45,
          40,
          42,
          39,
          44,
          44,
          44,
          42,
          42,
          43,
          40,
          53,
          77,
          93,
          117,
          161,
          142,
          119,
          72
        ]
      },
      "hourly_units": {
        "time": "iso8601",
        "sulphur_dioxide": "μg/m³",
        "carbon_monoxide": "μg/m³",
        "nitrogen_dioxide": "μg/m³",
        "carbon_dioxide": "ppm",
        "wind_speed_10m": "km/h",
        "wind_direction_10m": "°"
      }
    },
    {
      "name": "Reventador",
      "latitude": -0.0775,
      "longitude": -77.6561,
      "hourly": {
        "time": [
          "2025-09-24T00:00",
          "2025-09-24T01:00",
          "2025-09-24T02:00",
          "2025-09-24T03:00",
          "2025-09-24T04:00",
          "2025-09-24T05:00",
          "2025-09-24T06:00",
          "2025-09-24T07:00",
          "2025-09-24T08:00",
          "2025-09-24T09:00",
          "2025-09-24T10:00",
          "2025-09-24T11:00",
          "2025-09-24T12:00",
          "2025-09-24T13:00",
          "2025-09-24T14:00",
          "2025-09-24T15:00",
          "2025-09-24T16:00",
          "2025-09-24T17:00",
          "2025-09-24T18:00",
          "2025-09-24T19:00",
          "2025-09-24T20:00",
          "2025-09-24T21:00",
          "2025-09-24T22:00",
          "2025-09-24T23:00"
        ],
        "sulphur_dioxide": [
          1.3,
          1.2,
          1.1,
          1,
          0.9,
          0.7,
          0.8,
          1.2,
          1.7,
          2.2,
          2.4,
          2.5,
          2.8,
          3.4,
          4.1,
          4.6,
          4.6,
          4.4,
          4,
          3.5,
          2.9,
          2.5,
          2.3,
          2.3
        ],
        "carbon_monoxide": [
          824,
          794,
          724,
          654,
          591,
          528,
          478,
          445,
          426,
          421,
          447,
          488,
          496,
          434,
          339,
          278,
          286,
          329,
          368,
          382,
          392,
          426,
          512,
          623
        ],
        "nitrogen_dioxide": [
          4.9,
          5,
          5.2,
          5.1,
          4.5,
          3.7,
          3,
          2.5,
          2.2,
          2.1,
          2.4,
          3,
          3.1,
          2.4,
          1.2,
          0.4,
          0.2,
          0.4,
          0.6,
          0.6,
          0.6,
          1.2,
          2.9,
          5.2
        ],
        "carbon_dioxide": [
          448,
          458,
          469,
          478,
          483,
          487,
          490,
          495,
          501,
          500,
          489,
          472,
          457,
          446,
          436,
          430,
          428,
          429,
          429,
          427,
          424,
          424,
          430,
          438
        ],
        "wind_speed_10m": [
          4.5,
          2.2,
          3.9,
          5.2,
          6,
          5.7,
          6.3,
          4,
          2.5,
          1.8,
          3.6,
          2.6,
          2.9,
          1.8,
          1.1,
          4.5,
          5.7,
          7.9,
          9.2,
          7.5,
          4.7,
          4.4,
          2.9,
          1.3
        ],
        "wind_direction_10m": [
          61,
          9,
          292,
          286,
          287,
          288,
          283,
          280,
          278,
          281,
          270,
          236,
          240,
          270,
          252,
          119,
          125,
          120,
          111,
          107,
          113,
          171,
          180,
          236
        ]
      },
      "hourly_units": {
        "time": "iso8601",
        "sulphur_dioxide": "μg/m³",
        "carbon_monoxide": "μg/m³",
        "nitrogen_dioxide": "μg/m³",
        "carbon_dioxide": "ppm",
        "wind_speed_10m": "km/h",
        "wind_direction_10m": "°"
      }
    },
    {
      "name": "Poás",
      "latitude": 10.19751,
      "longitude": -84.23084,
      "hourly": {
        "time": [
          "2025-09-24T00:00",
          "2025-09-24T01:00",
          "2025-09-24T02:00",
          "2025-09-24T03:00",
          "2025-09-24T04:00",
          "2025-09-24T05:00",
          "2025-09-24T06:00",
          "2025-09-24T07:00",
          "2025-09-24T08:00",
          "2025-09-24T09:00",
          "2025-09-24T10:00",
          "2025-09-24T11:00",
          "2025-09-24T12:00",
          "2025-09-24T13:00",
          "2025-09-24T14:00",
          "2025-09-24T15:00",
          "2025-09-24T16:00",
          "2025-09-24T17:00",
          "2025-09-24T18:00",
          "2025-09-24T19:00",
          "2025-09-24T20:00",
          "2025-09-24T21:00",
          "2025-09-24T22:00",
          "2025-09-24T23:00"
        ],
        "sulphur_dioxide": [
          3.1,
          3.1,
          3,
          2.9,
          2.5,
          2.1,
          1.7,
          1.5,
          1.5,
          1.5,
          1.6,
          1.9,
          2.1,
          2.3,
          2.4,
          2.5,
          2.5,
          2.4,
          2.4,
          2.5,
          2.6,
          2.8,
          3,
          3.3
        ],
        "carbon_monoxide": [
          169,
          169,
          165,
          162,
          158,
          154,
          151,
          149,
          148,
          146,
          143,
          139,
          135,
          129,
          123,
          119,
          119,
          121,
          123,
          126,
          129,
          132,
          135,
          139
        ],
        "nitrogen_dioxide": [
          18.9,
          20.3,
          22.2,
          22.9,
          21.5,
          18.9,
          16.3,
          13.7,
          11,
          9.1,
          8.9,
          9.5,
          9.3,
          7.4,
          4.8,
          2.8,
          1.9,
          1.5,
          1.4,
          1.2,
          1.4,
          2.8,
          6.5,
          11.5
        ],
        "carbon_dioxide": [
          437,
          441,
          444,
          447,
          449,
          449,
          450,
          451,
          452,
          451,
          448,
          443,
          439,
          435,
          431,
          429,
          429,
          431,
          432,
          431,
          428,
          428,
          431,
          436
        ],
        "wind_speed_10m": [
          8,
          11.3,
          11.6,
          12,
          12.5,
          12.7,
          14.1,
          14.3,
          13.3,
          13.7,
          14.3,
          14.2,
          15,
          15.1,
          15.5,
          15.3,
          14.9,
          13.5,
          11.8,
          7,
          6.5,
          4.6,
          3.3,
          4.1
        ],
        "wind_direction_10m": [
          27,
          31,
          30,
          33,
          33,
          35,
          38,
          39,
          33,
          30,
          34,
          36,
          35,
          38,
          42,
          49,
          58,
          65,
          63,
          69,
          90,
          108,
          77,
          38
        ]
      },
      "hourly_units": {
        "time": "iso8601",
        "sulphur_dioxide": "μg/m³",
        "carbon_monoxide": "μg/m³",
        "nitrogen_dioxide": "μg/m³",
        "carbon_dioxide": "ppm",
        "wind_speed_10m": "km/h",
        "wind_direction_10m": "°"
      }
    },
    {
      "name": "Stromboli",
      "latitude": 38.789,
      "longitude": 15.213,
      "hourly": {
        "time": [
          "2025-09-24T00:00",
          "2025-09-24T01:00",
          "2025-09-24T02:00",
          "2025-09-24T03:00",
          "2025-09-24T04:00",
          "2025-09-24T05:00",
          "2025-09-24T06:00",
          "2025-09-24T07:00",
          "2025-09-24T08:00",
          "2025-09-24T09:00",
          "2025-09-24T10:00",
          "2025-09-24T11:00",
          "2025-09-24T12:00",
          "2025-09-24T13:00",
          "2025-09-24T14:00",
          "2025-09-24T15:00",
          "2025-09-24T16:00",
          "2025-09-24T17:00",
          "2025-09-24T18:00",
          "2025-09-24T19:00",
          "2025-09-24T20:00",
          "2025-09-24T21:00",
          "2025-09-24T22:00",
          "2025-09-24T23:00"
        ],
        "sulphur_dioxide": [
          0.9,
          0.9,
          1.1,
          1.1,
          1.1,
          1.3,
          1,
          1.2,
          1.3,
          1.5,
          1.4,
          1,
          1,
          1,
          0.6,
          0.5,
          0.3,
          0.2,
          0.2,
          0.2,
          0.2,
          0.1,
          0.2,
          0.3
        ],
        "carbon_monoxide": [
          122,
          122,
          122,
          122,
          120,
          121,
          121,
          120,
          121,
          122,
          120,
          120,
          118,
          117,
          116,
          117,
          116,
          117,
          114,
          115,
          116,
          117,
          116,
          115
        ],
        "nitrogen_dioxide": [
          2.1,
          2.2,
          2,
          1.4,
          2.1,
          2,
          2.1,
          2.8,
          2.5,
          2.8,
          2.3,
          1.8,
          1.3,
          1.2,
          0.8,
          0.7,
          0.7,
          0.8,
          0.8,
          0.8,
          0.8,
          0.9,
          0.9,
          0.8
        ],
        "carbon_dioxide": [
          435,
          435,
          436,
          436,
          436,
          436,
          436,
          436,
          437,
          437,
          437,
          436,
          436,
          436,
          436,
          436,
          437,
          438,
          438,
          438,
          437,
          436,
          435,
          434
        ],
        "wind_speed_10m": [
          5.4,
          2.6,
          0.7,
          2.8,
          1.9,
          1.3,
          5.2,
          5.6,
          4.1,
          3.1,
          8.8,
          1,
          4.3,
          9.7,
          15.8,
          18.1,
          21,
          17.1,
          16.4,
          15.4,
          16,
          15.5,
          18.9,
          19.9
        ],
        "wind_direction_10m": [
          176,
          164,
          360,
          40,
          68,
          214,
          245,
          255,
          255,
          216,
          251,
          225,
          246,
          268,
          269,
          257,
          265,
          285,
          296,
          291,
          284,
          288,
          305,
          312
        ]
      },
      "hourly_units": {
        "time": "iso8601",
        "sulphur_dioxide": "μg/m³",
        "carbon_monoxide": "μg/m³",
        "nitrogen_dioxide": "μg/m³",
        "carbon_dioxide": "ppm",
        "wind_speed_10m": "km/h",
        "wind_direction_10m": "°"
      }
    },
    {
      "name": "Aso",
      "latitude": 32.884,
      "longitude": 131.104,
      "hourly": {
        "time": [
          "2025-09-24T00:00",
          "2025-09-24T01:00",
          "2025-09-24T02:00",
          "2025-09-24T03:00",
          "2025-09-24T04:00",
          "2025-09-24T05:00",
          "2025-09-24T06:00",
          "2025-09-24T07:00",
          "2025-09-24T08:00",
          "2025-09-24T09:00",
          "2025-09-24T10:00",
          "2025-09-24T11:00",
          "2025-09-24T12:00",
          "2025-09-24T13:00",
          "2025-09-24T14:00",
          "2025-09-24T15:00",
          "2025-09-24T16:00",
          "2025-09-24T17:00",
          "2025-09-24T18:00",
          "2025-09-24T19:00",
          "2025-09-24T20:00",
          "2025-09-24T21:00",
          "2025-09-24T22:00",
          "2025-09-24T23:00"
        ],
        "sulphur_dioxide": [
          0.2,
          0.3,
          0.4,
          0.5,
          0.6,
          0.6,
          0.6,
          0.5,
          0.4,
          0.4,
          0.5,
          0.6,
          0.6,
          0.5,
          0.3,
          0.1,
          0,
          0,
          0,
          0,
          0,
          0,
          0,
          0
        ],
        "carbon_monoxide": [
          146,
          145,
          142,
          140,
          137,
          135,
          135,
          140,
          147,
          153,
          158,
          163,
          164,
          158,
          148,
          140,
          136,
          133,
          132,
          133,
          136,
          138,
          138,
          137
        ],
        "nitrogen_dioxide": [
          2.2,
          1.7,
          1.1,
          0.7,
          0.6,
          0.7,
          1.1,
          2.3,
          3.8,
          4.7,
          4.5,
          3.7,
          3.1,
          2.9,
          2.8,
          2.6,
          2.2,
          1.7,
          1.4,
          1.3,
          1.3,
          1.4,
          1.5,
          1.6
        ],
        "carbon_dioxide": [
          440,
          435,
          430,
          427,
          426,
          426,
          427,
          429,
          432,
          436,
          442,
          449,
          454,
          454,
          451,
          448,
          447,
          446,
          447,
          451,
          456,
          457,
          451,
          440
        ],
        "wind_speed_10m": [
          19.9,
          20,
          17.6,
          17.3,
          15.5,
          16.6,
          17.2,
          15.9,
          13.1,
          10.2,
          7.9,
          8.2,
          7.9,
          10,
          6.8,
          7.4,
          8.7,
          5.6,
          5.5,
          8.4,
          8,
          7.6,
          8,
          8
        ],
        "wind_direction_10m": [
          125,
          129,
          139,
          137,
          134,
          138,
          143,
          147,
          148,
          148,
          141,
          142,
          156,
          159,
          148,
          129,
          135,
          135,
          148,
          149,
          170,
          161,
          153,
          153
        ]
      },
      "hourly_units": {
        "time": "iso8601",
        "sulphur_dioxide": "μg/m³",
        "carbon_monoxide": "μg/m³",
        "nitrogen_dioxide": "μg/m³",
        "carbon_dioxide": "ppm",
        "wind_speed_10m": "km/h",
        "wind_direction_10m": "°"
      }
    },
    {
      "name": "Ibu",
      "latitude": 1.488,
      "longitude": 127.63,
      "hourly": {
        "time": [
          "2025-09-24T00:00",
          "2025-09-24T01:00",
          "2025-09-24T02:00",
          "2025-09-24T03:00",
          "2025-09-24T04:00",
          "2025-09-24T05:00",
          "2025-09-24T06:00",
          "2025-09-24T07:00",
          "2025-09-24T08:00",
          "2025-09-24T09:00",
          "2025-09-24T10:00",
          "2025-09-24T11:00",
          "2025-09-24T12:00",
          "2025-09-24T13:00",
          "2025-09-24T14:00",
          "2025-09-24T15:00",
          "2025-09-24T16:00",
          "2025-09-24T17:00",
          "2025-09-24T18:00",
          "2025-09-24T19:00",
          "2025-09-24T20:00",
          "2025-09-24T21:00",
          "2025-09-24T22:00",
          "2025-09-24T23:00"
        ],
        "sulphur_dioxide": [
          1,
          1.2,
          1.5,
          1.7,
          1.6,
          1.3,
          1.1,
          0.9,
          0.6,
          0.5,
          0.5,
          0.6,
          0.6,
          0.6,
          0.5,
          0.4,
          0.4,
          0.3,
          0.3,
          0.3,
          0.3,
          0.3,
          0.4,
          0.5
        ],
        "carbon_monoxide": [
          122,
          119,
          114,
          111,
          112,
          115,
          120,
          126,
          133,
          144,
          164,
          188,
          203,
          201,
          191,
          179,
          168,
          157,
          149,
          147,
          147,
          145,
          137,
          126
        ],
        "nitrogen_dioxide": [
          0.4,
          0.4,
          0.3,
          0.3,
          0.3,
          0.3,
          0.3,
          0.4,
          0.5,
          0.6,
          0.7,
          0.7,
          0.8,
          0.8,
          0.9,
          0.9,
          0.9,
          0.9,
          0.9,
          0.9,
          0.9,
          0.9,
          0.8,
          0.6
        ],
        "carbon_dioxide": [
          435,
          432,
          431,
          431,
          430,
          430,
          431,
          434,
          438,
          446,
          459,
          475,
          490,
          504,
          516,
          526,
          532,
          534,
          533,
          530,
          523,
          510,
          485,
          455
        ],
        "wind_speed_10m": [
          3.6,
          6.8,
          8.7,
          9.8,
          12.3,
          11.8,
          10.5,
          9.5,
          7,
          4.6,
          2.7,
          2.6,
          3.1,
          3.4,
          4.2,
          3.9,
          4.3,
          4.5,
          4.2,
          4.2,
          4,
          4.2,
          4,
          3.1
        ],
        "wind_direction_10m": [
          233,
          238,
          240,
          242,
          238,
          239,
          239,
          241,
          235,
          231,
          203,
          164,
          159,
          148,
          121,
          112,
          114,
          104,
          110,
          110,
          117,
          121,
          117,
          135
        ]
      },
      "hourly_units": {
        "time": "iso8601",
        "sulphur_dioxide": "μg/m³",
        "carbon_monoxide": "μg/m³",
        "nitrogen_dioxide": "μg/m³",
        "carbon_dioxide": "ppm",
        "wind_speed_10m": "km/h",
        "wind_direction_10m": "°"
      }
    },
    {
      "name": "Shiveluch",
      "latitude": 56.653,
      "longitude": 161.36,
      "hourly": {
        "time": [
          "2025-09-24T00:00",
          "2025-09-24T01:00",
          "2025-09-24T02:00",
          "2025-09-24T03:00",
          "2025-09-24T04:00",
          "2025-09-24T05:00",
          "2025-09-24T06:00",
          "2025-09-24T07:00",
          "2025-09-24T08:00",
          "2025-09-24T09:00",
          "2025-09-24T10:00",
          "2025-09-24T11:00",
          "2025-09-24T12:00",
          "2025-09-24T13:00",
          "2025-09-24T14:00",
          "2025-09-24T15:00",
          "2025-09-24T16:00",
          "2025-09-24T17:00",
          "2025-09-24T18:00",
          "2025-09-24T19:00",
          "2025-09-24T20:00",
          "2025-09-24T21:00",
          "2025-09-24T22:00",
          "2025-09-24T23:00"
        ],
        "sulphur_dioxide": [
          0.1,
          0.1,
          0.1,
          0.1,
          0.1,
          0.1,
          0.1,
          0.1,
          0.1,
          0.1,
          0.1,
          0.1,
          0.1,
          0.1,
          0.1,
          0.1,
          0.1,
          0.1,
          0.1,
          0.1,
          0.1,
          0.1,
          0.1,
          0.1
        ],
        "carbon_monoxide": [
          130,
          130,
          131,
          131,
          131,
          131,
          131,
          131,
          130,
          130,
          130,
          130,
          130,
          130,
          130,
          130,
          130,
          129,
          129,
          129,
          129,
          129,
          130,
          130
        ],
        "nitrogen_dioxide": [
          0.1,
          0.1,
          0.1,
          0.1,
          0.1,
          0.1,
          0.1,
          0.1,
          0.2,
          0.2,
          0.2,
          0.2,
          0.2,
          0.2,
          0.3,
          0.3,
          0.3,
          0.3,
          0.3,
          0.3,
          0.3,
          0.3,
          0.2,
          0.2
        ],
        "carbon_dioxide": [
          430,
          430,
          431,
          431,
          431,
          431,
          431,
          431,
          432,
          432,
          432,
          432,
          432,
          432,
          432,
          432,
          432,
          432,
          432,
          432,
          431,
          431,
          431,
          431
        ],
        "wind_speed_10m": [
          50,
          50.7,
          50.4,
          51.9,
          50.6,
          46.7,
          38.5,
          32.6,
          32.2,
          32.6,
          33.1,
          31.1,
          28.6,
          27.3,
          25.8,
          24,
          21.9,
          20.7,
          19.2,
          17.7,
          16.3,
          16,
          16.3,
          15.6
        ],
        "wind_direction_10m": [
          285,
          287,
          290,
          294,
          297,
          301,
          305,
          307,
          310,
          312,
          313,
          313,
          312,
          311,
          311,
          311,
          311,
          310,
          308,
          308,
          305,
          301,
          295,
          293
        ]
      },
      "hourly_units": {
        "time": "iso8601",
        "sulphur_dioxide": "μg/m³",
        "carbon_monoxide": "μg/m³",
        "nitrogen_dioxide": "μg/m³",
        "carbon_dioxide": "ppm",
        "wind_speed_10m": "km/h",
        "wind_direction_10m": "°"
      }
    }
  ]
}